epf3/__init__.py
epf3/parser.py
epf3-0.1.dist-info/DESCRIPTION.rst
epf3-0.1.dist-info/METADATA
epf3-0.1.dist-info/RECORD
epf3-0.1.dist-info/WHEEL
epf3-0.1.dist-info/metadata.json
epf3-0.1.dist-info/top_level.txt
