Metadata-Version: 2.0
Name: epf3
Version: 0.1
Summary: A Python 3 library for parsing and processing iTunes EPF files.
Home-page: UNKNOWN
Author: High Summit LLC
Author-email: UNKNOWN
License: UNKNOWN
Keywords: itunes enterprise partner feed epf 3
Platform: UNKNOWN
Classifier: Development Status :: 3 - Alpha
Classifier: Intended Audience :: Developers
Classifier: Programming Language :: Python :: 3.6
